sample_api_client/__init__.py
sample_api_client/api/__init__.py
sample_api_client/api/default/__init__.py
sample_api_client/api/default/get_list.py
sample_api_client/client.py
sample_api_client/errors.py
sample_api_client/models/__init__.py
sample_api_client/py.typed
sample_api_client/types.py
test.py
chintan_sample_api_client-1.0.2.dist-info/METADATA
chintan_sample_api_client-1.0.2.dist-info/WHEEL
chintan_sample_api_client-1.0.2.dist-info/RECORD
